[{"Central Sphere":"","State":"Andaman and Nicobar Islands ","Zone":"","District":"","Class of Employment":"Agriculture","Category/Grade":"Unskilled","Designation/Skill Set":"","Effective_from (dd/mm/yyyy)":"01.07.2021","Basic /day":"","HRA/day":"","VDA /day":"","Special Allowance/Day":"","Daily Rate":499,"Basic /month":"","HRA/month":"","VDA /month":"","Special Allowance/month":"","Monthly Rate":12974},{"Central Sphere":"","State":"Andaman and Nicobar Islands ","Zone":"","District":"","Class of Employment":"Agriculture","Category/Grade":"Semi Skilled","Designation/Skill Set":"","Effective_from (dd/mm/yyyy)":"01.07.2021","Basic /day":"","HRA/day":"","VDA /day":"","Special Allowance/Day":"","Daily Rate":556,"Basic /month":"","HRA/month":"","VDA /month":"","Special Allowance/month":"","Monthly Rate":14456},{"Central Sphere":"","State":"Andaman and Nicobar Islands ","Zone":"","District":"","Class of Employment":"Agriculture","Category/Grade":"Skilled","Designation/Skill Set":"","Effective_from (dd/mm/yyyy)":"01.07.2021","Basic /day":"","HRA/day":"","VDA /day":"","Special Allowance/Day":"","Daily Rate":641,"Basic /month":"","HRA/month":"","VDA /month":"","Special Allowance/month":"","Monthly Rate":16666},{"Central Sphere":"","State":"Andaman and Nicobar Islands ","Zone":"","District":"","Class of Employment":"Agriculture","Category/Grade":"Clerical","Designation/Skill Set":"","Effective_from (dd/mm/yyyy)":"01.07.2021","Basic /day":"","HRA/day":"","VDA /day":"","Special Allowance/Day":"","Daily Rate":641,"Basic /month":"","HRA/month":"","VDA /month":"","Special Allowance/month":"","Monthly Rate":16666},{"Central Sphere":"","State":"Andaman and Nicobar Islands ","Zone":"","District":"","Class of Employment":"Agriculture","Category/Grade":"Highly Skilled","Designation/Skill Set":"","Effective_from (dd/mm/yyyy)":"01.07.2021","Basic /day":"","HRA/day":"","VDA /day":"","Special Allowance/Day":"","Daily Rate":699,"Basic /month":"","HRA/month":"","VDA /month":"","Special Allowance/month":"","Monthly Rate":18174},{"Central Sphere":"","State":"Andaman and Nicobar Islands ","Zone":"","District":"","Class of Employment":"Shops & Commercial Establishments","Category/Grade":"Unskilled","Designation/Skill Set":"","Effective_from (dd/mm/yyyy)":"01.07.2021","Basic /day":"","HRA/day":"","VDA /day":"","Special Allowance/Day":"","Daily Rate":499,"Basic /month":"","HRA/month":"","VDA /month":"","Special Allowance/month":"","Monthly Rate":12974},{"Central Sphere":"","State":"Andaman and Nicobar Islands ","Zone":"","District":"","Class of Employment":"Shops & Commercial Establishments","Category/Grade":"Semi Skilled","Designation/Skill Set":"","Effective_from (dd/mm/yyyy)":"01.07.2021","Basic /day":"","HRA/day":"","VDA /day":"","Special Allowance/Day":"","Daily Rate":556,"Basic /month":"","HRA/month":"","VDA /month":"","Special Allowance/month":"","Monthly Rate":14456},{"Central Sphere":"","State":"Andaman and Nicobar Islands ","Zone":"","District":"","Class of Employment":"Shops & Commercial Establishments","Category/Grade":"Skilled","Designation/Skill Set":"","Effective_from (dd/mm/yyyy)":"01.07.2021","Basic /day":"","HRA/day":"","VDA /day":"","Special Allowance/Day":"","Daily Rate":641,"Basic /month":"","HRA/month":"","VDA /month":"","Special Allowance/month":"","Monthly Rate":16666},{"Central Sphere":"","State":"Andaman and Nicobar Islands ","Zone":"","District":"","Class of Employment":"Shops & Commercial Establishments","Category/Grade":"Clerical","Designation/Skill Set":"","Effective_from (dd/mm/yyyy)":"01.07.2021","Basic /day":"","HRA/day":"","VDA /day":"","Special Allowance/Day":"","Daily Rate":641,"Basic /month":"","HRA/month":"","VDA /month":"","Special Allowance/month":"","Monthly Rate":16666},{"Central Sphere":"","State":"Andaman and Nicobar Islands ","Zone":"","District":"","Class of Employment":"Shops & Commercial Establishments","Category/Grade":"Highly Skilled","Designation/Skill Set":"","Effective_from (dd/mm/yyyy)":"01.07.2021","Basic /day":"","HRA/day":"","VDA /day":"","Special Allowance/Day":"","Daily Rate":699,"Basic /month":"","HRA/month":"","VDA /month":"","Special Allowance/month":"","Monthly Rate":18174},{"Central Sphere":"","State":"Andaman and Nicobar Islands ","Zone":"","District":"","Class of Employment":"Wooden Furniture","Category/Grade":"Unskilled","Designation/Skill Set":"","Effective_from (dd/mm/yyyy)":"01.07.2021","Basic /day":"","HRA/day":"","VDA /day":"","Special Allowance/Day":"","Daily Rate":499,"Basic /month":"","HRA/month":"","VDA /month":"","Special Allowance/month":"","Monthly Rate":12974},{"Central Sphere":"","State":"Andaman and Nicobar Islands ","Zone":"","District":"","Class of Employment":"Wooden Furniture","Category/Grade":"Semi Skilled","Designation/Skill Set":"","Effective_from (dd/mm/yyyy)":"01.07.2021","Basic /day":"","HRA/day":"","VDA /day":"","Special Allowance/Day":"","Daily Rate":556,"Basic /month":"","HRA/month":"","VDA /month":"","Special Allowance/month":"","Monthly Rate":14456},{"Central Sphere":"","State":"Andaman and Nicobar Islands ","Zone":"","District":"","Class of Employment":"Wooden Furniture","Category/Grade":"Skilled","Designation/Skill Set":"","Effective_from (dd/mm/yyyy)":"01.07.2021","Basic /day":"","HRA/day":"","VDA /day":"","Special Allowance/Day":"","Daily Rate":641,"Basic /month":"","HRA/month":"","VDA /month":"","Special Allowance/month":"","Monthly Rate":16666},{"Central Sphere":"","State":"Andaman and Nicobar Islands ","Zone":"","District":"","Class of Employment":"Wooden Furniture","Category/Grade":"Clerical","Designation/Skill Set":"","Effective_from (dd/mm/yyyy)":"01.07.2021","Basic /day":"","HRA/day":"","VDA /day":"","Special Allowance/Day":"","Daily Rate":641,"Basic /month":"","HRA/month":"","VDA /month":"","Special Allowance/month":"","Monthly Rate":16666},{"Central Sphere":"","State":"Andaman and Nicobar Islands ","Zone":"","District":"","Class of Employment":"Wooden Furniture","Category/Grade":"Highly Skilled","Designation/Skill Set":"","Effective_from (dd/mm/yyyy)":"01.07.2021","Basic /day":"","HRA/day":"","VDA /day":"","Special Allowance/Day":"","Daily Rate":699,"Basic /month":"","HRA/month":"","VDA /month":"","Special Allowance/month":"","Monthly Rate":18174},{"Central Sphere":"","State":"Andaman and Nicobar Islands ","Zone":"","District":"","Class of Employment":"Construction/Maintenance of Roads or in Building Operations*","Category/Grade":"Unskilled","Designation/Skill Set":"","Effective_from (dd/mm/yyyy)":"01.07.2021","Basic /day":"","HRA/day":"","VDA /day":"","Special Allowance/Day":"","Daily Rate":499,"Basic /month":"","HRA/month":"","VDA /month":"","Special Allowance/month":"","Monthly Rate":12974},{"Central Sphere":"","State":"Andaman and Nicobar Islands ","Zone":"","District":"","Class of Employment":"Construction/Maintenance of Roads or in Building Operations*","Category/Grade":"Semi Skilled","Designation/Skill Set":"","Effective_from (dd/mm/yyyy)":"01.07.2021","Basic /day":"","HRA/day":"","VDA /day":"","Special Allowance/Day":"","Daily Rate":556,"Basic /month":"","HRA/month":"","VDA /month":"","Special Allowance/month":"","Monthly Rate":14456},{"Central Sphere":"","State":"Andaman and Nicobar Islands ","Zone":"","District":"","Class of Employment":"Construction/Maintenance of Roads or in Building Operations*","Category/Grade":"Skilled","Designation/Skill Set":"","Effective_from (dd/mm/yyyy)":"01.07.2021","Basic /day":"","HRA/day":"","VDA /day":"","Special Allowance/Day":"","Daily Rate":641,"Basic /month":"","HRA/month":"","VDA /month":"","Special Allowance/month":"","Monthly Rate":16666},{"Central Sphere":"","State":"Andaman and Nicobar Islands ","Zone":"","District":"","Class of Employment":"Construction/Maintenance of Roads or in Building Operations*","Category/Grade":"Clerical","Designation/Skill Set":"","Effective_from (dd/mm/yyyy)":"01.07.2021","Basic /day":"","HRA/day":"","VDA /day":"","Special Allowance/Day":"","Daily Rate":641,"Basic /month":"","HRA/month":"","VDA /month":"","Special Allowance/month":"","Monthly Rate":16666},{"Central Sphere":"","State":"Andaman and Nicobar Islands ","Zone":"","District":"","Class of Employment":"Construction/Maintenance of Roads or in Building Operations*","Category/Grade":"Highly Skilled","Designation/Skill Set":"","Effective_from (dd/mm/yyyy)":"01.07.2021","Basic /day":"","HRA/day":"","VDA /day":"","Special Allowance/Day":"","Daily Rate":699,"Basic /month":"","HRA/month":"","VDA /month":"","Special Allowance/month":"","Monthly Rate":18174},{"Central Sphere":"","State":"Andaman and Nicobar Islands ","Zone":"","District":"","Class of Employment":"Industrial Worker (loading and unloading)","Category/Grade":"Unskilled","Designation/Skill Set":"","Effective_from (dd/mm/yyyy)":"01.07.2021","Basic /day":"","HRA/day":"","VDA /day":"","Special Allowance/Day":"","Daily Rate":499,"Basic /month":"","HRA/month":"","VDA /month":"","Special Allowance/month":"","Monthly Rate":12974},{"Central Sphere":"","State":"Andaman and Nicobar Islands ","Zone":"","District":"","Class of Employment":"Industrial Worker (loading and unloading)","Category/Grade":"Semi Skilled","Designation/Skill Set":"","Effective_from (dd/mm/yyyy)":"01.07.2021","Basic /day":"","HRA/day":"","VDA /day":"","Special Allowance/Day":"","Daily Rate":556,"Basic /month":"","HRA/month":"","VDA /month":"","Special Allowance/month":"","Monthly Rate":14456},{"Central Sphere":"","State":"Andaman and Nicobar Islands ","Zone":"","District":"","Class of Employment":"Industrial Worker (loading and unloading)","Category/Grade":"Skilled","Designation/Skill Set":"","Effective_from (dd/mm/yyyy)":"01.07.2021","Basic /day":"","HRA/day":"","VDA /day":"","Special Allowance/Day":"","Daily Rate":641,"Basic /month":"","HRA/month":"","VDA /month":"","Special Allowance/month":"","Monthly Rate":16666},{"Central Sphere":"","State":"Andaman and Nicobar Islands ","Zone":"","District":"","Class of Employment":"Industrial Worker (loading and unloading)","Category/Grade":"Clerical","Designation/Skill Set":"","Effective_from (dd/mm/yyyy)":"01.07.2021","Basic /day":"","HRA/day":"","VDA /day":"","Special Allowance/Day":"","Daily Rate":641,"Basic /month":"","HRA/month":"","VDA /month":"","Special Allowance/month":"","Monthly Rate":16666},{"Central Sphere":"","State":"Andaman and Nicobar Islands ","Zone":"","District":"","Class of Employment":"Industrial Worker (loading and unloading)","Category/Grade":"Highly Skilled","Designation/Skill Set":"","Effective_from (dd/mm/yyyy)":"01.07.2021","Basic /day":"","HRA/day":"","VDA /day":"","Special Allowance/Day":"","Daily Rate":699,"Basic /month":"","HRA/month":"","VDA /month":"","Special Allowance/month":"","Monthly Rate":18174}]